ttktooltip.py
ttktooltip-1.1.dist-info/licenses/LICENSE
ttktooltip-1.1.dist-info/METADATA
ttktooltip-1.1.dist-info/WHEEL
ttktooltip-1.1.dist-info/top_level.txt
ttktooltip-1.1.dist-info/RECORD
